nordvpn_switcher_pro/__init__.py
nordvpn_switcher_pro/api_client.py
nordvpn_switcher_pro/core.py
nordvpn_switcher_pro/exceptions.py
nordvpn_switcher_pro/settings.py
nordvpn_switcher_pro/ui.py
nordvpn_switcher_pro/windows_controller.py
nordvpn_switcher_pro-2.0.1.dist-info/licenses/LICENSE
nordvpn_switcher_pro-2.0.1.dist-info/METADATA
nordvpn_switcher_pro-2.0.1.dist-info/WHEEL
nordvpn_switcher_pro-2.0.1.dist-info/top_level.txt
nordvpn_switcher_pro-2.0.1.dist-info/RECORD
