Metadata-Version: 2.4
Name: nordvpn-switcher-pro
Version: 2.0.1
Summary: An advanced Python library to automate NordVPN server switching on Windows.
Home-page: https://github.com/Sebastian7700/nordvpn-switcher-pro
Author: Sebastian Hanisch
Author-email: contact.sebastian.hanisch@gmail.com
Project-URL: Bug Reports, https://github.com/Sebastian7700/nordvpn-switcher-pro/issues
Project-URL: Source, https://github.com/Sebastian7700/nordvpn-switcher-pro/
Keywords: nordvpn vpn switcher automation web-scraping ip-rotation rotate-ip windows api
Classifier: Development Status :: 5 - Production/Stable
Classifier: Intended Audience :: Developers
Classifier: Topic :: System :: Networking
Classifier: Topic :: Internet
Classifier: Topic :: Software Development :: Libraries :: Python Modules
Classifier: License :: OSI Approved :: MIT License
Classifier: Programming Language :: Python :: 3
Classifier: Programming Language :: Python :: 3.10
Classifier: Programming Language :: Python :: 3.11
Classifier: Programming Language :: Python :: 3.12
Classifier: Programming Language :: Python :: 3.13
Classifier: Operating System :: Microsoft :: Windows
Requires-Python: >=3.10
License-File: LICENSE
Requires-Dist: requests>=2.20.0
Requires-Dist: questionary>=1.10.0
Requires-Dist: fake-useragent>=1.2.0
Dynamic: author
Dynamic: author-email
Dynamic: classifier
Dynamic: description
Dynamic: description-content-type
Dynamic: home-page
Dynamic: keywords
Dynamic: license-file
Dynamic: project-url
Dynamic: requires-dist
Dynamic: requires-python
Dynamic: summary
